{
  "project_info": {
    "project_number": "643176833831",
    "project_id": "appavaluos-4a027",
    "storage_bucket": "appavaluos-4a027.firebasestorage.app"
  },
  "client": [
    {
      "client_info": {
        "mobilesdk_app_id": "1:643176833831:android:56aa3a9906e5baabe7ff02",
        "android_client_info": {
          "package_name": "mx.itson.moviles"
        }
      },
      "oauth_client": [],
      "api_key": [
        {
          "current_key": "AIzaSyCNIoeIxCt-c5veAji08CEvhaKUGvR0VmM"
        }
      ],
      "services": {
        "appinvite_service": {
          "other_platform_oauth_client": []
        }
      }
    }
  ],
  "configuration_version": "1"
}